{
  "name": "Ida McKinney",
  "age": 26,
  "address": {
    "street": "Ilimim Way",
    "city": "Lortubhu",
    "state": "NY",
    "zip": "45637"
  },
  "contact": {
    "phone": "(544) 845-9117",
    "servicePhone": "800965794"
  },
  "birthday": "1988-06-07T23:22:13.349Z",
  "ip": "35.207.225.9",
  "foo": "bar",
  "profile": {
    "about": "Awo ha azahi juj bi poz tipriig omi be nummu ikaje ven lajakaw buhepumif dutso. Gem ba ana ru ke cit kamla ofa sazzaw ma caja hub si ecobazaz oga. Bideva hajcic suro zug ibno hazenon giocuore wagcin bini wag he ifo. Gojemma iba of fezlehob ik zibi gitbeziv dib georu vebko efa keugeba ba dognu av eh. La afoofuzub haiwaac unobi acuwa ak uk nel kuwulat meadtet op nikdol hebacuh tos tekhanek icotemu. Luviv to vegkawep vak enizahel uwuci asudo ji of suhor zasnise tikhu gipevve.",
    "bio": "Ucsol bilziffa kizzabum hunna ovo douho vi bozmec tob ujo kampag nijradok kep waricej ohwe cevewzid uw fep. Edabam upo la cebezas zumapcuj onepuzdo bu la saowo se jegih zaduka sizziv bipo molvarte ihi vow. Acab fafatiku danu linpo okira ru wo wuwes wepmo uc gaod alazel. Vem kif aku abapi pogab be ifijuru jizus le jekiz ca wiocado mefoc fu. Ga defutak calizeb di vari oge cezmul aranusap umegi vem ovjizil cijoswa ilelilon fo papupmo jopibejup baneni. Rijcij kedfa ojje ami kufmahlun ad jutos laj girrej sutketig ab fo fuvabo husez lapfu dagekoge. Upta abuwipak kilpof lewij bewoeve ke gej so kasuweza bi tuhuruc waw selo siwne."
  },
  "apiKey": "4e86aa3469b965ae2e39353fac8e5bc34b9955c4fed1f49b0e06e0bcdec7b6b3",
  "currency": {
    "code": "MUR",
    "name": "Mauritius Rupee"
  }
}